MANIFEST.in
setup.py
wight/__init__.py
wight/errors.py
wight/load_data.py
wight/models.py
wight/api/__init__.py
wight/api/app.py
wight/api/config.py
wight/api/server.py
wight/api/handlers/__init__.py
wight/api/handlers/authentication.py
wight/api/handlers/base.py
wight/api/handlers/healthcheck.py
wight/api/handlers/load_test.py
wight/api/handlers/load_test_instance.py
wight/api/handlers/project.py
wight/api/handlers/team.py
wight/api/handlers/user.py
wight/cli/__init__.py
wight/cli/app.py
wight/cli/auth.py
wight/cli/base.py
wight/cli/config.py
wight/cli/default.py
wight/cli/load_test.py
wight/cli/project.py
wight/cli/target.py
wight/cli/team.py
wight/cli/user.py
wight/web/__init__.py
wight/web/app.py
wight/web/config.py
wight/web/server.py
wight/web/handlers/__init__.py
wight/web/handlers/base.py
wight/web/handlers/healthcheck.py
wight/web/handlers/report.py
wight/web/handlers/team.py
wight/web/static/css/bootstrap-responsive.css
wight/web/static/css/bootstrap-responsive.min.css
wight/web/static/css/bootstrap.css
wight/web/static/css/bootstrap.min.css
wight/web/static/css/nv.d3.css
wight/web/static/css/wight.css
wight/web/static/img/glyphicons-halflings-white.png
wight/web/static/img/glyphicons-halflings.png
wight/web/static/js/bootstrap.js
wight/web/static/js/bootstrap.min.js
wight/web/static/js/d3.v2.min.js
wight/web/static/js/diff.js
wight/web/static/js/fisheye.js
wight/web/static/js/jquery-2.0.0.min.js
wight/web/static/js/legend.js
wight/web/static/js/line.js
wight/web/static/js/nv.d3.min.js
wight/web/static/js/report.js
wight/web/static/js/trend.js
wight/web/templates/base.html
wight/web/templates/diff.html
wight/web/templates/report.html
wight/web/templates/team.html
wight/web/templates/trend.html
wight/worker/__init__.py
wight/worker/bench_configuration.py
wight/worker/config.py
wight/worker/repository.py
wight/worker/runners.py