Metadata-Version: 1.1
Name: wight
Version: 0.2.10
Summary: wight is a load testing scheduling and tracking tool.
Home-page: http://github.com/heynemann/wight/
Author: Bernardo Heynemann
Author-email: heynemann@gmail.com
License: MIT
Keywords: test testing load performance profile profiling
Platform: UNKNOWN
Classifier: Development Status :: 4 - Beta
Classifier: Intended Audience :: Developers
Classifier: License :: OSI Approved :: MIT License
Classifier: Natural Language :: English
Classifier: Operating System :: MacOS
Classifier: Operating System :: POSIX
Classifier: Operating System :: Unix
Classifier: Operating System :: OS Independent
Classifier: Programming Language :: Python :: 2.6
Classifier: Programming Language :: Python :: 2.7
Classifier: Topic :: Software Development :: Testing
